atol/__init__.py
atol/client.py
atol/const.py
atol/errors.py
atol_client-1.14.6.dist-info/LICENSE.txt
atol_client-1.14.6.dist-info/METADATA
atol_client-1.14.6.dist-info/WHEEL
atol_client-1.14.6.dist-info/top_level.txt
atol_client-1.14.6.dist-info/RECORD
