Metadata-Version: 2.1
Name: atol-client
Version: 1.14.6
Summary: Client for ATOL POS API
Home-page: https://github.com/sir-go/atol-client
Author: Sergei Michenko
Author-email: mserg@tih.ru
License: MIT
Classifier: Programming Language :: Python :: 3
Classifier: License :: OSI Approved :: MIT License
Requires-Python: >=3.6
License-File: LICENSE.txt
Requires-Dist: requests
